lifepo4weredPy/__init__.py
lifepo4weredPy/defines.py
lifepo4weredPy/functions.py
lifepo4weredPy/lifepo4weredSO.py
lifepo4weredPy/variablesEnum.py
lifepo4weredPy-0.1.1.dist-info/DESCRIPTION.rst
lifepo4weredPy-0.1.1.dist-info/METADATA
lifepo4weredPy-0.1.1.dist-info/RECORD
lifepo4weredPy-0.1.1.dist-info/WHEEL
lifepo4weredPy-0.1.1.dist-info/metadata.json
lifepo4weredPy-0.1.1.dist-info/top_level.txt
