Metadata-Version: 2.0
Name: lifepo4weredPy
Version: 0.1.1
Summary: A wrapper to enable lifepo4wered SO library to Python.
Home-page: https://github.com/fredericklussier/Lifepo4weredPy
Author: Frederick Lussier
Author-email: frederick.lussier@hotmail.com
License: MIT
Download-URL: https://github.com/fredericklussier/Lifepo4weredPy/0.1.1
